filehandler/__init__.py
filehandler/filehandler.py
filehandler6027-1.1.2.dist-info/licenses/LICENSE
filehandler6027-1.1.2.dist-info/licenses/LICENSE_local
filehandler6027-1.1.2.dist-info/METADATA
filehandler6027-1.1.2.dist-info/WHEEL
filehandler6027-1.1.2.dist-info/top_level.txt
filehandler6027-1.1.2.dist-info/RECORD
