Metadata-Version: 2.4
Name: filehandler6027
Version: 1.1.2
Summary: A simple cross-platform file handling utility
Author-email: Charlie Sky <your@email.com>
License: MIT License
License-File: LICENSE
License-File: LICENSE_local
Dynamic: license-file
